MANIFEST.in
ez_setup.py
setup.cfg
setup.py
tox.ini
mwlib/__init__.py
mwlib/docbook44grammar.py
mwlib/docbookwriter.py
mwlib.docbook.egg-info/PKG-INFO
mwlib.docbook.egg-info/SOURCES.txt
mwlib.docbook.egg-info/dependency_links.txt
mwlib.docbook.egg-info/entry_points.txt
mwlib.docbook.egg-info/namespace_packages.txt
mwlib.docbook.egg-info/not-zip-safe
mwlib.docbook.egg-info/requires.txt
mwlib.docbook.egg-info/top_level.txt
tests/test_docbookwriter.py
tools/build_rng_grammar.py