Metadata-Version: 1.0
Name: mwlib.docbook
Version: 0.1.0
Summary: docbook writer for mwlib
Home-page: http://code.pediapress.com/
Author: pediapress.com
Author-email: info@pediapress.com
License: BSD License
Platform: UNKNOWN
